rdtsc/__init__.py
rdtsc/rdtsc.dylib
rdtsc-0.2.1.dist-info/DESCRIPTION.rst
rdtsc-0.2.1.dist-info/METADATA
rdtsc-0.2.1.dist-info/RECORD
rdtsc-0.2.1.dist-info/WHEEL
rdtsc-0.2.1.dist-info/metadata.json
rdtsc-0.2.1.dist-info/top_level.txt
